antfinagentframework/__init__.py
antfinagentframework/agent/__init__.py
antfinagentframework/agent/agent.py
antfinagentframework/agent/agent_manager.py
antfinagentframework/agent/agent_model.py
antfinagentframework/agent/input_object.py
antfinagentframework/agent/output_object.py
antfinagentframework/agent/action/__init__.py
antfinagentframework/agent/action/knowledge/__init__.py
antfinagentframework/agent/action/knowledge/knowledge.py
antfinagentframework/agent/action/knowledge/knowledge_manager.py
antfinagentframework/agent/action/knowledge/default/__init__.py
antfinagentframework/agent/action/knowledge/default/default_knowledge.py
antfinagentframework/agent/action/knowledge/default/default_knowledge.yaml
antfinagentframework/agent/action/knowledge/embedding/__init__.py
antfinagentframework/agent/action/knowledge/embedding/embedding.py
antfinagentframework/agent/action/knowledge/embedding/openai_embedding.py
antfinagentframework/agent/action/knowledge/reader/__init__.py
antfinagentframework/agent/action/knowledge/reader/reader.py
antfinagentframework/agent/action/knowledge/reader/file/__init__.py
antfinagentframework/agent/action/knowledge/reader/file/docx_reader.py
antfinagentframework/agent/action/knowledge/reader/file/file_reader.py
antfinagentframework/agent/action/knowledge/reader/file/pdf_reader.py
antfinagentframework/agent/action/knowledge/reader/file/pptx_reader.py
antfinagentframework/agent/action/knowledge/reader/file/web_pdf_reader.py
antfinagentframework/agent/action/knowledge/store/__init__.py
antfinagentframework/agent/action/knowledge/store/chroma_store.py
antfinagentframework/agent/action/knowledge/store/document.py
antfinagentframework/agent/action/knowledge/store/query.py
antfinagentframework/agent/action/knowledge/store/store.py
antfinagentframework/agent/action/tool/__init__.py
antfinagentframework/agent/action/tool/enum.py
antfinagentframework/agent/action/tool/tool.py
antfinagentframework/agent/action/tool/tool_manager.py
ant_fin_agent_framework-0.0.2.dist-info/LICENSE
ant_fin_agent_framework-0.0.2.dist-info/METADATA
ant_fin_agent_framework-0.0.2.dist-info/WHEEL
ant_fin_agent_framework-0.0.2.dist-info/top_level.txt
ant_fin_agent_framework-0.0.2.dist-info/RECORD
