Metadata-Version: 2.1
Name: ant-fin-agent-framework
Version: 0.0.2
Summary: AntFinAgentFramework is a framework for developing applications powered by multi-agent base on large language model.
Home-page: https://gitee.com/ant-fin-agent-framework/ant-fin-agent-framework
Author: AntGroup
Author-email: jerry.zzw@antgroup.com
Classifier: Programming Language :: Python :: 3.10
Classifier: License :: OSI Approved :: Apache Software License
Classifier: Operating System :: OS Independent
License-File: LICENSE
Requires-Dist: requests >=2.31.0
Requires-Dist: cffi >=1.15.1
Requires-Dist: flask >=2.2
Requires-Dist: werkzeug >=2.2.2
Requires-Dist: langchain >=0.0.352
Requires-Dist: langchain-core >=0.1.3
Requires-Dist: openai >=1.13.3
Requires-Dist: tiktoken >=0.5.2
Requires-Dist: loguru >=0.7.2
Requires-Dist: flask-cors >=4.0.0
Requires-Dist: SQLAlchemy >=2.0.25
Requires-Dist: pydantic >=2.6.4
Requires-Dist: gunicorn >=21.2.0
Requires-Dist: chromadb >=0.4.24
Requires-Dist: sphinx >=7.2.6
Requires-Dist: sphinx-rtd-theme >=2.0.0
Requires-Dist: aliyun-log-python-sdk >=0.8.8
Requires-Dist: googleapis-common-protos >=1.63.0
Requires-Dist: myst-parser >=2.0.0
Requires-Dist: pdfminer.six
